[
  {
    "section": "Spring Class Changes",
    "announcements": [
      {
        "title": "Thursday 6 PM Class @ East Liberty",
        "description": "- will become a Gentle Yoga class effective March 2nd",
        "expires": "2017-02-31T00:00:00.000-05:00"
      },
      {
        "title": "Tuesday 9am Yoga 2 Class @ Squirrel Hill",
        "description": "- will become a Yoga 1 level class effective March 7th",
        "expires": "2017-02-31T00:00:00.000-05:00"
      },
      {
        "title": "Tuesday 9:30am Yoga 1 @ Squirrel Hill",
        "description": "- will become a Gentle Yoga class effective March 7th",
        "expires": "2017-02-31T00:00:00.000-05:00"       
      },
      {
        "title": "Final Monday 4:30 PM Yoga 1 class @ East Liberty",
        "description": "- will run on February 27th",
        "expires": "2017-02-10T00:00:00.000-05:00"       
      },     
      {
        "title": "Saturday Chair Yoga class @ North Hills",
        "description": "- will become a Gentle Yoga class and will run 2-3:15pm effective March 4th",
        "expires": "2017-02-31T00:00:00.000-05:00"       
      },
      {
        "title": "Monday 6pm Yoga 2 @Squirrel Hill",
        "description": "- will become an Ashtanga Yoga class effective March 6th",
        "expires": "2017-02-31T00:00:00.000-05:00"       
      }
    ]
  },
  {
    "section": "Apple Pay",
    "announcements": [
      {
        "title": "Apple Pay now accepted",
        "description": "- Buy class passes and workshops from our website using your iPhone and Touch ID",
        "expires": "2017-10-01T00:00:00.000-05:00"
      }
    ]
  }
]
